README.rst
setup.py
paipa/__init__.py
paipa/coroutines.py
paipa/counter.py
paipa/debug_reporter.py
paipa/debugger.py
paipa/glue.py
paipa/iterables.py
paipa/threaded.py
paipa.egg-info/PKG-INFO
paipa.egg-info/SOURCES.txt
paipa.egg-info/dependency_links.txt
paipa.egg-info/requires.txt
paipa.egg-info/top_level.txt
test/test_pipeline_debugger.py
test/test_thread_pipeline.py