Metadata-Version: 1.1
Name: paipa
Version: 0.3.2
Summary: Python pipeline library. Maori: (noun) pipe.
Home-page: https://github.com/stylight/python-paipa
Author: python-paipa contributors
Author-email: python-tribe@stylight.com
License: Apache Software License 2.0
Platform: UNKNOWN
Classifier: Intended Audience :: Developers
Classifier: License :: OSI Approved
Classifier: License :: OSI Approved :: Apache Software License
Classifier: Programming Language :: Python
Classifier: Programming Language :: Python :: 2.7
Classifier: Programming Language :: Python :: 3.4
Classifier: Programming Language :: Python :: 3.5
Classifier: Programming Language :: Python :: 3.6
Classifier: Topic :: Software Development :: Libraries :: Python Modules
